[
  {
    "title": "Le Ali della Libertà",
    "release_year": 1994,
    "movie_length": 142,
    "genre": "Drama",
    "language": "Italiano",
    "imdb_url": "https://www.imdb.com/title/tt0111161/",
    "imdb_image": "https://m.media-amazon.com/images/M/MV5BNDE3ODcxYzMtY2YzZC00NmNlLWJiNDMtZDViZWM2MzIxZDYwXkEyXkFqcGdeQXVyNjAwNDUxODI@._V1_QL75_UX190_CR0,2,190,281_.jpg"
  },
  {
    "title": "Il Padrino",
    "release_year": 1972,
    "movie_length": 175,
    "genre": "Crime",
    "language": "Italiano",
    "imdb_url": "https://www.imdb.com/title/tt0068646/",
    "imdb_image": "https://m.media-amazon.com/images/M/MV5BMTg5M2QzNmMtMjkyYS00YzhlLWIzMjItMGZiOTkxY2EwNmVkXkEyXkFqcGdeQXVyODc0OTEyNDU@._V1_QL75_UY281_CR9,0,190,281_.jpg"
  },
  {
    "title": "Il Cavaliere Oscuro",
    "release_year": 2008,
    "movie_length": 152,
    "genre": "Azione",
    "language": "Italiano",
    "imdb_url": "https://www.imdb.com/title/tt0468569/",
    "imdb_image": "https://m.media-amazon.com/images/M/MV5BMTMxNTMwODM0NF5BMl5BanBnXkFtZTcwODAyMTk2Mw@@._V1_QL75_UX190_CR0,0,190,281_.jpg"
  },
  {
    "title": "Il Padrino - Parte II",
    "release_year": 1974,
    "movie_length": 202,
    "genre": "Crime",
    "language": "Italiano",
    "imdb_url": "https://www.imdb.com/title/tt0071562/",
"imdb_image": "https://m.media-amazon.com/images/M/MV5BY2M0MTI2MTAtYzhmYi00ZDFjLTlhZDMtOGQ4MDE1YWQ0ZDljXkEyXkFqcGdeQXVyMTYzMDM0NTU@._V1_QL75_UY281_CR2,0,190,281_.jpg"
  },
  {
    "title": "Il Signore degli Anelli - Il Ritorno del Re",
    "release_year": 2003,
    "movie_length": 201,
    "genre": "Avventura",
    "language": "Italiano",
    "imdb_url": "https://www.imdb.com/title/tt0167260/",
    "imdb_image": "https://m.media-amazon.com/images/M/MV5BZGExNmU3YTQtOTFmZi00NmQ0LWE5ODAtYmE0YTAzOGFjZDc1XkEyXkFqcGdeQXVyNjI0MTA1MTM@._V1_QL75_UY281_CR3,0,190,281_.jpg"
  },
  {
    "title": "Pulp Fiction",
    "release_year": 1994,
    "movie_length": 154,
    "genre": "Crime",
    "language": "Italiano",
    "imdb_url": "https://www.imdb.com/title/tt0110912/",
    "imdb_image": "https://m.media-amazon.com/images/M/MV5BMDAyOWI5ZGItMDM2MS00M2ZiLWE1OWItYzI1ZGFhYTVlMzhjXkEyXkFqcGdeQXVyMTYzMDM0NTU@._V1_QL75_UY281_CR3,0,190,281_.jpg"
  },
  {
    "title": "Schindler's List",
    "release_year": 1993,
    "movie_length": 195,
    "genre": "Biografico",
    "language": "Italiano",
    "imdb_url": "https://www.imdb.com/title/tt0108052/",
    "imdb_image": "https://m.media-amazon.com/images/M/MV5BYzA2N2FlODItMDUzYS00NjhmLTg5OGYtMGQ3NWQ4ODZmYWNhXkEyXkFqcGdeQXVyMTYzMDM0NTU@._V1_QL75_UY281_CR3,0,190,281_.jpg"
  },
  {
    "title": "Il Signore degli Anelli - La Compagnia dell'Anello",
    "release_year": 2001,
    "movie_length": 178,
    "genre": "Avventura",
    "language": "Italiano",
    "imdb_url": "https://www.imdb.com/title/tt0120737/",
    "imdb_image": "https://m.media-amazon.com/images/M/MV5BNzc3MjIyNzMtNmE1Yi00YTVmLTlkZWQtNjc0ZWZlNTY0NTg5XkEyXkFqcGdeQXVyMTYzMDM0NTU@._V1_QL75_UY281_CR4,0,190,281_.jpg"
  },
  {
    "title": "Fight Club",
    "release_year": 1999,
    "movie_length": 139,
    "genre": "Drama",
    "language": "Italiano",
    "imdb_url": "https://www.imdb.com/title/tt0137523/",
    "imdb_image": "https://m.media-amazon.com/images/M/MV5BNTExODU3YzYtNzlkMC00NzZlLWFkODYtZmFmMTc2MjZhOWRmXkEyXkFqcGdeQXVyODIyOTEyMzY@._V1_QL75_UY281_CR5,0,190,281_.jpg"
  },
  {
    "title": "Il Signore degli Anelli - Le Due Torri",
    "release_year": 2002,
    "movie_length": 179,
    "genre": "Avventura",
    "language": "Italiano",
    "imdb_url": "https://www.imdb.com/title/tt0167261/",
    "imdb_image": "https://m.media-amazon.com/images/M/MV5BMDZmMTc0MDMtOTAzMS00MTkxLWJiMDQtMmIzODBlNTQ1YjFhXkEyXkFqcGdeQXVyNjI0MTA1MTM@._V1_QL75_UY281_CR11,0,190,281_.jpg"
  },
  {
    "title": "Forrest Gump",
    "release_year": 1994,
    "movie_length": 142,
    "genre": "Drama",
    "language": "Italiano",
    "imdb_url": "https://www.imdb.com/title/tt0109830/",
    "imdb_image": "https://m.media-amazon.com/images/M/MV5BY2I0NTI3MGEtYWJiMy00YmM3LWI2ZWYtY2YwYjRkMmUwNzliXkEyXkFqcGdeQXVyMTYzMDM0NTU@._V1_QL75_UX190_CR0,2,190,281_.jpg"
  },
  {
    "title": "Il Gladiatore",
    "release_year": 2000,
    "movie_length": 155,
    "genre": "Azione",
    "language": "Italiano",
    "imdb_url": "https://www.imdb.com/title/tt0172495/",
    "imdb_image": "https://m.media-amazon.com/images/M/MV5BNzIxODdmYjAtYmExZi00M2Y5LWJjNDgtMTc2OWM4MmM0N2E1XkEyXkFqcGdeQXVyMTYzMDM0NTU@._V1_QL75_UY281_CR4,0,190,281_.jpg"
  },
  {
    "title": "Inception",
    "release_year": 2010,
    "movie_length": 148,
    "genre": "Azione",
    "language": "Italiano",
    "imdb_url": "https://www.imdb.com/title/tt1375666/",
    "imdb_image": "https://m.media-amazon.com/images/M/MV5BMWVjOTM1MzAtOTk3ZS00YmUyLThkNDgtNDhhNjU4YTI2MWMxXkEyXkFqcGdeQXVyMTYzMDM0NTU@._V1_QL75_UY281_CR4,0,190,281_.jpg"
  },
  {
    "title": "Lo Hobbit - Un Viaggio Inaspettato",
    "release_year": 2012,
    "movie_length": 169,
    "genre": "Avventura",
    "language": "Italiano",
    "imdb_url": "https://www.imdb.com/title/tt0903624/",
    "imdb_image": "https://m.media-amazon.com/images/M/MV5BNTU1MDQ3YzgtMTZlOS00YjM3LThkYjUtZjI2YWY0ZGNlNzlkXkEyXkFqcGdeQXVyNzI1NzMxNzM@._V1_QL75_UY281_CR4,0,190,281_.jpg"
  },
  {
    "title": "Il Buono, il Brutto, il Cattivo",
    "release_year": 1966,
    "movie_length": 178,
    "genre": "Western",
    "language": "Italiano",
    "imdb_url": "https://www.imdb.com/title/tt0060196/",
    "imdb_image": "https://m.media-amazon.com/images/M/MV5BNjJlYmNkZGItM2NhYy00MjlmLTk5NmQtNjg1NmM2ODU4OTMwXkEyXkFqcGdeQXVyMjUzOTY1NTc@._V1_QL75_UX190_CR0,2,190,281_.jpg"
  }
]